setup.py
fastAQ/__init__.py
fastAQ/fastaInfo.py
fastAQ/fastq2fasta.py
fastAQ/fastqInfo.py
fastAQ/sequenceOperations.py
fastAQ/trimming.py
fastAQ/commandLineTools/__init__.py
fastAQ/commandLineTools/fasta.py
fastAQ/commandLineTools/fastq.py
fastAQ/commandLineTools/fastq2fasta.py
fastaq.egg-info/PKG-INFO
fastaq.egg-info/SOURCES.txt
fastaq.egg-info/dependency_links.txt
fastaq.egg-info/top_level.txt