Metadata-Version: 1.1
Name: fastaq
Version: 0.30
Summary: fastAQ is a very and super lightweight package for working with FASTA/FASTQ sequences
Home-page: https://github.com/Jverma/fastAQ
Author: Janu Verma
Author-email: jv367@cornell.edu
License: MIT
Keywords: Genomics,Quantitative genetics,python
Platform: Linux
Platform: Mac OSX
Platform: Windows
Platform: Unix
Classifier: Development Status :: 3 - Alpha
Classifier: Intended Audience :: Developers
Classifier: Intended Audience :: Science/Research
Classifier: Operating System :: OS Independent
Classifier: Programming Language :: Python
Classifier: Topic :: Software Development :: Libraries :: Python Modules
